gbase8sdeploy/__init__.py
gbase8sdeploy/cluster.py
gbase8sdeploy/cm.py
gbase8sdeploy/dblog.py
gbase8sdeploy/dbspace.py
gbase8sdeploy/driver_manager.py
gbase8sdeploy/env.py
gbase8sdeploy/er.py
gbase8sdeploy/er_node.py
gbase8sdeploy/grid.py
gbase8sdeploy/instance.py
gbase8sdeploy/machine.py
gbase8sdeploy/onconfig.py
gbase8sdeploy/product.py
gbase8sdeploy/replicate.py
gbase8sdeploy/replicate_set.py
gbase8sdeploy/server.py
gbase8sdeploy/server_pool.py
gbase8sdeploy/sqlhosts.py
gbase8sdeploy/ssh_session.py
gbase8sdeploy-1.4.2.dist-info/METADATA
gbase8sdeploy-1.4.2.dist-info/WHEEL
gbase8sdeploy-1.4.2.dist-info/top_level.txt
gbase8sdeploy-1.4.2.dist-info/RECORD
